<?xml version="1.0" encoding="UTF-8"?>
<billStatus>
  <bill>
    <notes />
    <congress>115</congress>
    <committees>
      <billCommittees>
        <item>
          <activities>
            <item>
              <date>2017-05-03T14:22:59Z</date>
              <name>Referred to</name>
            </item>
          </activities>
          <type>Standing</type>
          <chamber>Senate</chamber>
          <systemCode>ssfi00</systemCode>
          <name>Finance Committee</name>
          <subcommittees />
        </item>
      </billCommittees>
    </committees>
    <committeeReports />
    <cboCostEstimates />
    <title>Gigabit Opportunity Act</title>
    <laws />
    <updateDate>2018-08-28T20:26:27Z</updateDate>
    <relatedBills>
      <item>
        <type>HR</type>
        <number>828</number>
        <latestTitle>Investing in Opportunity Act</latestTitle>
        <congress>115</congress>
        <latestAction>
          <actionDate>2017-02-02</actionDate>
          <text>Referred to the House Committee on Ways and Means.</text>
        </latestAction>
        <relationshipDetails>
          <item>
            <type>Related bill</type>
            <identifiedBy>CRS</identifiedBy>
          </item>
        </relationshipDetails>
      </item>
      <item>
        <type>S</type>
        <number>293</number>
        <latestTitle>Investing in Opportunity Act</latestTitle>
        <congress>115</congress>
        <latestAction>
          <actionDate>2017-02-02</actionDate>
          <text>Read twice and referred to the Committee on Finance.</text>
        </latestAction>
        <relationshipDetails>
          <item>
            <type>Related bill</type>
            <identifiedBy>CRS</identifiedBy>
          </item>
        </relationshipDetails>
      </item>
      <item>
        <type>HR</type>
        <number>2870</number>
        <latestTitle>Gigabit Opportunity Act</latestTitle>
        <congress>115</congress>
        <latestAction>
          <actionDate>2017-06-16</actionDate>
          <text>Referred to the Subcommittee on Communications and Technology.</text>
        </latestAction>
        <relationshipDetails>
          <item>
            <type>Identical bill</type>
            <identifiedBy>CRS</identifiedBy>
          </item>
        </relationshipDetails>
      </item>
    </relatedBills>
    <version>1.0.0</version>
    <actions>
      <actionTypeCounts>
        <referredToCommittee>1</referredToCommittee>
        <introducedInSenate>1</introducedInSenate>
      </actionTypeCounts>
      <item>
        <actionDate>2017-05-03</actionDate>
        <committee>
          <systemCode>ssfi00</systemCode>
          <name>Finance Committee</name>
        </committee>
        <links />
        <sourceSystem>
          <name>Senate</name>
          <code>0</code>
        </sourceSystem>
        <text>Read twice and referred to the Committee on Finance.</text>
        <type>IntroReferral</type>
      </item>
      <item>
        <actionDate>2017-05-03</actionDate>
        <actionCode>10000</actionCode>
        <committee />
        <text>Introduced in Senate</text>
        <links />
        <type>IntroReferral</type>
        <sourceSystem>
          <name>Library of Congress</name>
          <code>9</code>
        </sourceSystem>
      </item>
      <actionByCounts>
        <senate>2</senate>
      </actionByCounts>
    </actions>
    <sponsors>
      <item>
        <fullName>Sen. Capito, Shelley Moore [R-WV]</fullName>
        <identifiers>
          <lisID>1676</lisID>
          <gpoId>8223</gpoId>
          <bioguideId>C001047</bioguideId>
        </identifiers>
        <bioguideId>C001047</bioguideId>
        <lastName>CAPITO</lastName>
        <firstName>SHELLEY</firstName>
        <party>R</party>
        <byRequestType />
        <middleName>MOORE</middleName>
        <state>WV</state>
      </item>
    </sponsors>
    <billType>S</billType>
    <policyArea>
      <name>Taxation</name>
    </policyArea>
    <recordedVotes />
    <billNumber>1013</billNumber>
    <titles>
      <item>
        <chamberCode />
        <titleType>Short Titles as Introduced</titleType>
        <parentTitleType />
        <chamberName />
        <title>Gigabit Opportunity Act</title>
      </item>
      <item>
        <chamberCode />
        <titleType>Official Title as Introduced</titleType>
        <parentTitleType />
        <chamberName />
        <title>A bill to amend the Internal Revenue Code of 1986 to provide tax benefits for investments in gigabit opportunity zones.</title>
      </item>
      <item>
        <chamberCode />
        <titleType>Display Title</titleType>
        <parentTitleType />
        <chamberName />
        <title>Gigabit Opportunity Act</title>
      </item>
      <item>
        <chamberCode />
        <titleType>(Extracted from GPO) Short Titles as Introduced</titleType>
        <parentTitleType />
        <chamberName />
        <title>Gigabit Opportunity Act</title>
      </item>
    </titles>
    <originChamber>Senate</originChamber>
    <subjects>
      <billSubjects>
        <legislativeSubjects>
          <item>
            <name>Administrative law and regulatory procedures</name>
          </item>
          <item>
            <name>Business investment and capital</name>
          </item>
          <item>
            <name>Capital gains tax</name>
          </item>
          <item>
            <name>Economic development</name>
          </item>
          <item>
            <name>Federal Communications Commission (FCC)</name>
          </item>
          <item>
            <name>Financial services and investments</name>
          </item>
          <item>
            <name>Income tax deductions</name>
          </item>
          <item>
            <name>Income tax exclusion</name>
          </item>
          <item>
            <name>Income tax rates</name>
          </item>
          <item>
            <name>Internet and video services</name>
          </item>
          <item>
            <name>Securities</name>
          </item>
          <item>
            <name>State and local government operations</name>
          </item>
        </legislativeSubjects>
        <policyArea>
          <name>Taxation</name>
        </policyArea>
      </billSubjects>
    </subjects>
    <cosponsors>
      <item>
        <lastName>Coons</lastName>
        <middleName>A.</middleName>
        <sponsorshipWithdrawnDate />
        <bioguideId>C001088</bioguideId>
        <fullName>Sen. Coons, Christopher A. [D-DE]</fullName>
        <identifiers>
          <bioguideId>C001088</bioguideId>
          <lisID>1984</lisID>
          <gpoId>8297</gpoId>
        </identifiers>
        <sponsorshipDate>2017-06-21</sponsorshipDate>
        <state>DE</state>
        <firstName>Christopher</firstName>
        <isOriginalCosponsor>False</isOriginalCosponsor>
        <party>D</party>
      </item>
    </cosponsors>
    <introducedDate>2017-05-03</introducedDate>
    <calendarNumbers />
    <latestAction>
      <actionDate>2017-05-03</actionDate>
      <links />
      <text>Read twice and referred to the Committee on Finance.</text>
    </latestAction>
    <amendments />
    <summaries>
      <billSummaries>
        <item>
          <updateDate>2017-05-03T04:00:00Z</updateDate>
          <actionDate>2017-05-03</actionDate>
          <lastSummaryUpdateDate>2017-09-11T20:08:35Z</lastSummaryUpdateDate>
          <text><![CDATA[<p><b>Gigabit Opportunity Act </b></p> <p>This bill amends the Internal Revenue Code to authorize the designation of qualified gigabit opportunity zones in low-income communities and to provide tax incentives for investments in the zones.</p> <p>Governors may submit nominations for a limited number of qualified gigabit opportunity zones in low-income communities to the Department of the Treasury for certification and designation. Governors must give particular consideration to areas that: </p> <ul> <li> are facing obstacles to economic development due to a lack of geographic broadband coverage or speed; </li> <li> are the focus of mutually reinforcing state, local, or private economic development initiatives;</li> <li> are poised for economic growth that requires access to high speed broadband for commercial purposes; and</li> <li>represent the areas of a state where such service would result in the highest return on investment. </li> </ul> <p>For eligible taxpayers that sell certain broadband services, the bill allows: (1) deferrals, reductions, or exemptions from taxes on capital gains invested in certain property used to provide broadband services in a zone (depending on how long the property is held), and (2) immediate expensing of the costs of the property. </p> <p>The bill also allows tax-exempt private activity bonds to be used for certain broadband projects in the zones. </p> <p>Within one year of enactment of this bill, the Federal Communications Commission must publish a Uniform Model Broadband Deployment Act containing laws for the state regulation of the deployment of broadband services. Qualified zones must adopt either the Act or laws comparable to the Act. </p>]]></text>
          <actionDesc>Introduced in Senate</actionDesc>
          <versionCode>00</versionCode>
          <name>Introduced in Senate</name>
        </item>
      </billSummaries>
    </summaries>
    <createDate>2017-05-04T00:26:48Z</createDate>
  </bill>
  <dublinCore xmlns:dc="http://purl.org/dc/elements/1.1/">
    <dc:format>text/xml</dc:format>
    <dc:language>EN</dc:language>
    <dc:rights>Pursuant to Title 17 Section 105 of the United States Code, this file is not subject to copyright protection and is in the public domain.</dc:rights>
    <dc:contributor>Congressional Research Service, Library of Congress</dc:contributor>
    <dc:description>This file contains bill summaries and statuses for federal legislation. A bill summary describes the most significant provisions of a piece of legislation and details the effects the legislative text may have on current law and federal programs. Bill summaries are authored by the Congressional Research Service (CRS) of the Library of Congress. As stated in Public Law 91-510 (2 USC 166 (d)(6)), one of the duties of CRS is "to prepare summaries and digests of bills and resolutions of a public general nature introduced in the Senate or House of Representatives". For more information, refer to the User Guide that accompanies this file.</dc:description>
  </dublinCore>
</billStatus>

